CHANGES.txt
LICENSE.txt
MANIFEST.in
README.md
setup.cfg
setup.py
bin/rblcheck
bin/rblwatch
rblwatch/__init__.py
rblwatch/rblwatch.py
rblwatch.egg-info/PKG-INFO
rblwatch.egg-info/SOURCES.txt
rblwatch.egg-info/dependency_links.txt
rblwatch.egg-info/requires.txt
rblwatch.egg-info/top_level.txt