Metadata-Version: 1.2
Name: rblwatch
Version: 0.3.1
Summary: RBL lookups with Python
Home-page: https://github.com/drscream/rblwatch
Author: James Polera
Author-email: james@uncryptic.com
Maintainer: Thomas Merkel
Maintainer-email: tm@core.io
License: BSD
Keywords: rbl,blacklist,mail
Platform: UNKNOWN
Classifier: License :: OSI Approved :: BSD License
